{
    "id": 359,
    "common_name": "Dolgo Apple",
    "scientific_name": [
        "Malus 'Dolgo'"
    ],
    "other_name": [
        "Roseybloom",
        "Crabapple"
    ],
    "family": null,
    "origin": [
        "Russia"
    ],
    "type": "tree",
    "dimension": "Height:  35 feet",
    "dimensions": {
        "type": "Height",
        "min_value": 35,
        "max_value": 35,
        "unit": "feet"
    },
    "cycle": "Perennial",
    "attracts": [],
    "propagation": [
        "Grafting Propagation",
        "Budding",
        "Layering Propagation",
        "Budding",
        "Budding",
        "Whip Grafting Propagation",
        "Cleft Grafting Propagation",
        "Budding",
        "Inarching"
    ],
    "hardiness": {
        "min": "2",
        "max": "2"
    },
    "hardiness_location": {
        "full_url": "https://perenual.com/api/hardiness-map?species_id=359&size=og&key=sk-k0Dd66ebe3d09c08a6728",
        "full_iframe": "<iframe frameborder=0 scrolling=yes seamless=seamless width=1000 height=550 style='margin:auto;' src='https://perenual.com/api/hardiness-map?species_id=359&size=og&key=sk-k0Dd66ebe3d09c08a6728'></iframe>"
    },
    "watering": "Average",
    "depth_water_requirement": {
        "unit": "inches",
        "value": "2"
    },
    "volume_water_requirement": [],
    "watering_period": null,
    "watering_general_benchmark": {
        "value": "3-4",
        "unit": "days"
    },
    "plant_anatomy": [],
    "sunlight": [
        "full sun"
    ],
    "pruning_month": [
        "February",
        "March",
        "April",
        "May"
    ],
    "pruning_count": {
        "amount": 1,
        "interval": "yearly"
    },
    "seeds": 1,
    "maintenance": null,
    "care-guides": "http://perenual.com/api/species-care-guide-list?species_id=359&key=sk-k0Dd66ebe3d09c08a6728",
    "soil": [],
    "growth_rate": "High",
    "drought_tolerant": true,
    "salt_tolerant": true,
    "thorny": true,
    "invasive": false,
    "tropical": false,
    "indoor": false,
    "care_level": null,
    "pest_susceptibility": [],
    "pest_susceptibility_api": "Coming Soon",
    "flowers": false,
    "flowering_season": null,
    "flower_color": "",
    "cones": false,
    "fruits": true,
    "edible_fruit": true,
    "edible_fruit_taste_profile": "Coming Soon",
    "fruit_nutritional_value": "Coming Soon",
    "fruit_color": [
        "red",
        "yellow",
        "pink"
    ],
    "harvest_season": "Fall",
    "leaf": true,
    "leaf_color": [
        "green"
    ],
    "edible_leaf": false,
    "cuisine": true,
    "medicinal": true,
    "poisonous_to_humans": 0,
    "poisonous_to_pets": 0,
    "description": "Malus 'Dolgo' is an amazing plant species if you are looking for a reliable fruit tree that delivers a bounty of sweet apples for years. This robust apple tree grows vigorously and has excellent disease resistance. It bears large, bright red apples that are showy and sweet, perfect for eating and cooking. The fruit is small but is quite juicy and has a pleasant sweet-tart flavor. Its harvest time is from mid-September to early October, and Dolgo apples store well for long periods of time. Its showy white blossoms are a sight to behold in the spring, making it an attractive landscape addition for any garden. It's no wonder Dolgo apples are a favorite of apple lovers everywhere.",
    "default_image": {
        "license": 451,
        "license_name": "CC0 1.0 Universal (CC0 1.0) Public Domain Dedication",
        "license_url": "https://creativecommons.org/publicdomain/zero/1.0/",
        "original_url": "https://perenual.com/storage/species_image/359_malus_dolgo/og/apple-zieraepfel-wild-apple-tree-branch.jpg",
        "regular_url": "https://perenual.com/storage/species_image/359_malus_dolgo/regular/apple-zieraepfel-wild-apple-tree-branch.jpg",
        "medium_url": "https://perenual.com/storage/species_image/359_malus_dolgo/medium/apple-zieraepfel-wild-apple-tree-branch.jpg",
        "small_url": "https://perenual.com/storage/species_image/359_malus_dolgo/small/apple-zieraepfel-wild-apple-tree-branch.jpg",
        "thumbnail": "https://perenual.com/storage/species_image/359_malus_dolgo/thumbnail/apple-zieraepfel-wild-apple-tree-branch.jpg"
    },
    "other_images": "Upgrade Plan To Supreme For Access https://perenual.com/subscription-api-pricing. Im sorry"
}