{
    "id": 533,
    "common_name": "bugbane",
    "scientific_name": [
        "Actaea simplex (Atropurpurea Group) 'James Compton'"
    ],
    "other_name": [
        "cimicifuga"
    ],
    "family": "Ranunculaceae",
    "origin": [
        "Central",
        "west Asia"
    ],
    "type": "Shrub",
    "dimension": "4.00 to 6.00 feet",
    "dimensions": {
        "type": null,
        "min_value": 4,
        "max_value": 6,
        "unit": "feet"
    },
    "cycle": "Herbaceous Perennial",
    "attracts": [],
    "propagation": [
        "Division"
    ],
    "hardiness": {
        "min": "3",
        "max": "8"
    },
    "hardiness_location": {
        "full_url": "https://perenual.com/api/hardiness-map?species_id=533&size=og&key=sk-fAZY66f316387ceed6987",
        "full_iframe": "<iframe frameborder=0 scrolling=yes seamless=seamless width=1000 height=550 style='margin:auto;' src='https://perenual.com/api/hardiness-map?species_id=533&size=og&key=sk-fAZY66f316387ceed6987'></iframe>"
    },
    "watering": "Average",
    "depth_water_requirement": [],
    "volume_water_requirement": [],
    "watering_period": null,
    "watering_general_benchmark": {
        "value": null,
        "unit": "days"
    },
    "plant_anatomy": [],
    "sunlight": [
        "deep shade",
        "filtered shade",
        "part sun/part shade"
    ],
    "pruning_month": [
        "March",
        "April",
        "May"
    ],
    "pruning_count": {
        "amount": 2,
        "interval": "yearly"
    },
    "seeds": 0,
    "maintenance": "Low",
    "care-guides": "http://perenual.com/api/species-care-guide-list?species_id=533&key=sk-fAZY66f316387ceed6987",
    "soil": [
        "Humus rich",
        " Well-drained"
    ],
    "growth_rate": "Moderate",
    "drought_tolerant": true,
    "salt_tolerant": false,
    "thorny": false,
    "invasive": false,
    "tropical": false,
    "indoor": false,
    "care_level": "Medium",
    "pest_susceptibility": [
        "Rust"
    ],
    "pest_susceptibility_api": "Coming Soon",
    "flowers": true,
    "flowering_season": "Summer",
    "flower_color": "White",
    "cones": false,
    "fruits": true,
    "edible_fruit": false,
    "edible_fruit_taste_profile": "Coming Soon",
    "fruit_nutritional_value": "Coming Soon",
    "fruit_color": [],
    "harvest_season": "Fall",
    "leaf": true,
    "leaf_color": [],
    "edible_leaf": false,
    "cuisine": false,
    "medicinal": true,
    "poisonous_to_humans": 0,
    "poisonous_to_pets": 0,
    "description": "Bugbane is an amazing and attractive plant species that is perfect for many gardens. Its dark, purplish-brown foliage provides a stunning contrast to other garden plants. The species is also known for its tall spires of ivory-white flowers and its sweet, spicy fragrance. It is capable of providing a dramatic display when planted in masses and it is deer-resistant. On top of its good looks, Bugbane also attracts beneficial wildlife such as bees, butterflies, and hummingbirds. Finally, its foliage provides coverage and maintains moisture in gardens and landscapes in the summer. All of these features make Bugbane an amazing plant that should be considered for any garden.",
    "default_image": null,
    "other_images": "Upgrade Plan To Supreme For Access https://perenual.com/subscription-api-pricing. Im sorry"
}